navo/__init__.py
navo/_astropy_init.py
navo/conftest.py
navo/example_mod.py
navo/version.py
navo/data/README.rst
navo/example_subpkg/__init__.py
navo/example_subpkg/setup_package.py
navo/example_subpkg/tests/__init__.py
navo/extern/__init__.py
navo/tests/__init__.py
navo/tests/coveragerc
navo/tests/test_example.py
navo/utils/__init__.py
navo/utils/tests/__init__.py
navo-0.0.dev5.dist-info/METADATA
navo-0.0.dev5.dist-info/WHEEL
navo-0.0.dev5.dist-info/entry_points.txt
navo-0.0.dev5.dist-info/top_level.txt
navo-0.0.dev5.dist-info/RECORD
