Metadata-Version: 2.1
Name: navo
Version: 0.0.dev5
Summary: Collection of utilities to facilitate Virtual Observatory access
Home-page: https://github.com/NASA-NAVO/navo
Author: NAVO Developers
Author-email: UNKNOWN
License: BSD 3-Clause
Platform: UNKNOWN
Requires-Dist: astropy
